{
  "android": {
    "default": "App Name",
    "en": "App Name"
  },
  "iOS": {
    "default": {
      "title":"App name",
      "NSPhotoLibraryUsageDescription": null,
      "NSCameraUsageDescription": null,
      "NSMicrophoneUsageDescription": null,
      "NSLocationWhenInUseUsageDescription": null,
      "NSLocationAlwaysUsageDescription": null,
      "NSLocationAlwaysAndWhenInUseUsageDescription": null
    },
    "en": {
      "title": "App Name",
      "NSPhotoLibraryUsageDescription": null,
      "NSCameraUsageDescription": null,
      "NSMicrophoneUsageDescription": null,
      "NSLocationWhenInUseUsageDescription": null,
      "NSLocationAlwaysUsageDescription": null,
      "NSLocationAlwaysAndWhenInUseUsageDescription": null
    }
  }
}